<annotation>
	<folder></folder>
	<filename>50631041f74001aa_jpg.rf.86535271a5bf51fb4ed1535b47488a0e.jpg</filename>
	<path>50631041f74001aa_jpg.rf.86535271a5bf51fb4ed1535b47488a0e.jpg</path>
	<source>
		<database>roboflow.ai</database>
	</source>
	<size>
		<width>416</width>
		<height>416</height>
		<depth>3</depth>
	</size>
	<segmented>0</segmented>
	<object>
		<name>license-plate</name>
		<pose>Unspecified</pose>
		<truncated>0</truncated>
		<difficult>0</difficult>
		<occluded>0</occluded>
		<bndbox>
			<xmin>70</xmin>
			<xmax>81</xmax>
			<ymin>219</ymin>
			<ymax>239</ymax>
		</bndbox>
	</object>
	<object>
		<name>vehicle</name>
		<pose>Unspecified</pose>
		<truncated>0</truncated>
		<difficult>0</difficult>
		<occluded>0</occluded>
		<bndbox>
			<xmin>68</xmin>
			<xmax>395</xmax>
			<ymin>120</ymin>
			<ymax>276</ymax>
		</bndbox>
	</object>
</annotation>
