<annotation>
	<folder></folder>
	<filename>aca8821ff0368720_jpg.rf.3b2e4ceb9495c5fe04dedd841277b759.jpg</filename>
	<path>aca8821ff0368720_jpg.rf.3b2e4ceb9495c5fe04dedd841277b759.jpg</path>
	<source>
		<database>roboflow.ai</database>
	</source>
	<size>
		<width>416</width>
		<height>416</height>
		<depth>3</depth>
	</size>
	<segmented>0</segmented>
	<object>
		<name>license-plate</name>
		<pose>Unspecified</pose>
		<truncated>0</truncated>
		<difficult>0</difficult>
		<occluded>0</occluded>
		<bndbox>
			<xmin>6</xmin>
			<xmax>20</xmax>
			<ymin>92</ymin>
			<ymax>112</ymax>
		</bndbox>
	</object>
	<object>
		<name>license-plate</name>
		<pose>Unspecified</pose>
		<truncated>0</truncated>
		<difficult>0</difficult>
		<occluded>0</occluded>
		<bndbox>
			<xmin>129</xmin>
			<xmax>163</xmax>
			<ymin>87</ymin>
			<ymax>122</ymax>
		</bndbox>
	</object>
	<object>
		<name>vehicle</name>
		<pose>Unspecified</pose>
		<truncated>0</truncated>
		<difficult>0</difficult>
		<occluded>0</occluded>
		<bndbox>
			<xmin>1</xmin>
			<xmax>170</xmax>
			<ymin>1</ymin>
			<ymax>186</ymax>
		</bndbox>
	</object>
	<object>
		<name>vehicle</name>
		<pose>Unspecified</pose>
		<truncated>0</truncated>
		<difficult>0</difficult>
		<occluded>0</occluded>
		<bndbox>
			<xmin>1</xmin>
			<xmax>417</xmax>
			<ymin>2</ymin>
			<ymax>264</ymax>
		</bndbox>
	</object>
	<object>
		<name>vehicle</name>
		<pose>Unspecified</pose>
		<truncated>0</truncated>
		<difficult>0</difficult>
		<occluded>0</occluded>
		<bndbox>
			<xmin>86</xmin>
			<xmax>412</xmax>
			<ymin>1</ymin>
			<ymax>263</ymax>
		</bndbox>
	</object>
	<object>
		<name>vehicle</name>
		<pose>Unspecified</pose>
		<truncated>0</truncated>
		<difficult>0</difficult>
		<occluded>0</occluded>
		<bndbox>
			<xmin>398</xmin>
			<xmax>417</xmax>
			<ymin>40</ymin>
			<ymax>101</ymax>
		</bndbox>
	</object>
</annotation>
